juss/__init__.py
juss/admin.py
juss/apps.py
juss/middlewares.py
juss/static/admin/img/icon-addlink.svg
juss/static/admin/img/icon-changelink.svg
juss/static/admin/img/icon-deletelink.svg
juss/static/admin/img/icon-no.svg
juss/static/admin/img/icon-yes.svg
juss/static/admin/img/tooltag-add.svg
juss/static/juss/_button.scss
juss/static/juss/_dark.scss
juss/static/juss/_dashboard.scss
juss/static/juss/_form.scss
juss/static/juss/_light.scss
juss/static/juss/_login.scss
juss/static/juss/_message.scss
juss/static/juss/_navbar.scss
juss/static/juss/_table.scss
juss/static/juss/base.css
juss/static/juss/base.scss
juss/static/juss/check.svg
juss/static/juss/chevron-right.svg
juss/static/juss/feather.min.js
juss/static/juss/jdenticon.js
juss/static/juss/js.cookie.min.js
juss/static/juss/juss.css
juss/static/juss/juss.js
juss/static/juss/pure-min.css
juss/templates/admin/base.html
juss/templates/admin/filter.html
juss/templates/admin/index.html
juss/templates/admin/login.html
juss/templates/admin/search_form.html
juss/templates/juss/juss_menus.html
juss/templatetags/__init__.py
juss/templatetags/juss_menus.py
django_juss-0.2.8.dist-info/LICENSE
django_juss-0.2.8.dist-info/METADATA
django_juss-0.2.8.dist-info/WHEEL
django_juss-0.2.8.dist-info/top_level.txt
django_juss-0.2.8.dist-info/RECORD
